{
  "products": [
    {
      "id": "1",
      "product name": "Samsung Galaxy A51",
      "quantity": "422",
      "price": 900
    },
    {
      "id": "2",
      "product name": "Iphone 15",
      "quantity": 2000,
      "price": 1000
    },
    {
      "id": "3",
      "product name": "Huawei",
      "quantity": 5000,
      "price": 999.99
    },
    {
      "id": "3",
      "product name": "Addidas",
      "quantity": 100000,
      "price": 900
    },
    {
      "id": "3",
      "product name": "Addidas",
      "quantity": 100000,
      "price": 900
    },
    {
      "id": "3",
      "product name": "Addidas",
      "quantity": 100000,
      "price": 900
    },
    {
      "id": "3",
      "product name": "HP Pavilion",
      "quantity": 100000,
      "price": 900
    },
    {
      "id": "3",
      "product name": "Toyota",
      "quantity": 100000,
      "price": 900
    },
    {
      "id": "3",
      "product name": "Xiaomi",
      "quantity": 500,
      "price": 30000
    },
    {
      "id": "3",
      "product name": "PSP",
      "quantity": 500,
      "price": 2000
    },
    {
      "id": "3",
      "product name": "PS",
      "quantity": 500,
      "price": 60000
    },
    {
      "id": "3",
      "product name": "Nike",
      "quantity": 500,
      "price": 2000
    },
    {
      "id": "3",
      "product name": "Addidas",
      "quantity": 500,
      "price": 500
    },
    {
      "id": "3",
      "product name": "Kodak",
      "quantity": 500,
      "price": 20000
    },
    {
      "id": "3",
      "product name": "Letto",
      "quantity": 500,
      "price": 3000
    },
    {
      "id": "3",
      "product name": "Lee",
      "quantity": 500,
      "price": 2000
    },
    {
      "id": "3",
      "product name": "Apple",
      "quantity": 50,
      "price": 200
    },
    {
      "id": "3",
      "product name": "Linux",
      "quantity": 500,
      "price": 500000
    },
    {
      "id": "4",
      "product name": "Maxxis",
      "quantity": 500,
      "price": 12000
    },
    {
      "id": "5",
      "product name": "Stamp pad",
      "quantity": 500,
      "price": 20
    },
    {
      "id": "4",
      "product name": "Scissors",
      "quantity": 50,
      "price": 10
    },
    {
      "id": "4d096385-c68a-4187-a268-5ecc16dd1462",
      "product name": "Stapler",
      "quantity": 50,
      "price": 10
    },
    {
      "id": "7abee130-03f4-4700-b653-d129b35b4c09",
      "product name": "Levise",
      "quantity": 100,
      "price": 3000
    },
    {
      "id": "49858ee2-3bac-49ba-8c1a-5fae57f2e469",
      "product name": "HHey",
      "quantity": 11,
      "price": 0
    },
    {
      "id": "0d4639d8-b6b2-4c7d-b9ee-ed6cbdf8e404",
      "product name": "Wheel",
      "quantity": 100,
      "price": 100
    },
    {
      "id": "7ca86dc6-95b7-4124-9342-f23e1742916b",
      "product name": "Radio",
      "quantity": 100,
      "price": 200
    },
    {
      "id": "4fbcc790-5f2a-49ae-8386-7f80e00e5cd8",
      "product name": "Charger",
      "quantity": 100,
      "price": 2000
    }
  ]
}